myutil/__init__.py
myutil/path/__init__.py
myutil/path/path.py
myutil/spreadsheet/__init__.py
myutil/spreadsheet/spreadsheet_manager.py
myutil/spreadsheet/functions/__init__.py
myutil/spreadsheet/functions/type_convert.py
apsniper0673_util-0.1.9.dist-info/METADATA
apsniper0673_util-0.1.9.dist-info/WHEEL
apsniper0673_util-0.1.9.dist-info/top_level.txt
apsniper0673_util-0.1.9.dist-info/RECORD
