Metadata-Version: 2.4
Name: apsniper0673_util
Version: 0.1.9
Summary: My util for APSniper0673
Author: apsniper0673
Requires-Python: >=3.8
